nbconvert_reportlab/__init__.py
nbconvert_reportlab/exporter.py
nbconvert_reportlab/pdfimage.py
nbconvert_reportlab/rlmarkdown.py
nbconvert_reportlab-0.2.dist-info/entry_points.txt
nbconvert_reportlab-0.2.dist-info/LICENSE
nbconvert_reportlab-0.2.dist-info/WHEEL
nbconvert_reportlab-0.2.dist-info/METADATA
nbconvert_reportlab-0.2.dist-info/RECORD
